vartex/__init__.py
vartex/cli.py
vartex/temp.py
vartex/variable_reader.py
vartex/vartex.py
vartex-0.0.1.dist-info/LICENSE
vartex-0.0.1.dist-info/METADATA
vartex-0.0.1.dist-info/WHEEL
vartex-0.0.1.dist-info/entry_points.txt
vartex-0.0.1.dist-info/top_level.txt
vartex-0.0.1.dist-info/RECORD
