Metadata-Version: 2.1
Name: vartex
Version: 0.0.1
Summary: A CLI tool to generate multiple LaTeX files with different variables.
Author: Sahil Pattni
Author-email: Sahil Pattni <sahilpattni97+vartex@gmail.com>
Project-URL: Homepage, https://github.com/Sahil-Pattni/VarTex
Project-URL: Bug Tracker, https://github.com/Sahil-Pattni/VarTex/issues
Classifier: Programming Language :: Python :: 3
Classifier: License :: OSI Approved :: MIT License
Classifier: Operating System :: OS Independent
Requires-Python: >=3.7
License-File: LICENSE
